AUTHORS
CHANGES
LICENSE
MANIFEST.in
README
WIDGETS
setup.py
django_extrawidgets/__init__.py
django_extrawidgets/models.py
django_extrawidgets/validation.py
django_extrawidgets/views.py
django_extrawidgets/widgets.py
django_extrawidgets.egg-info/PKG-INFO
django_extrawidgets.egg-info/SOURCES.txt
django_extrawidgets.egg-info/dependency_links.txt
django_extrawidgets.egg-info/not-zip-safe
django_extrawidgets.egg-info/top_level.txt
django_extrawidgets/static/extrawidgets/rays.css
django_extrawidgets/static/extrawidgets/rays.js
django_extrawidgets/templatetags/__init__.py
django_extrawidgets/templatetags/rays_validation.py