Metadata-Version: 1.1
Name: django-extrawidgets
Version: 1
Summary: A project exploring the client-side of Django website development
Home-page: http://www.bitbucket.org/freakboy3742/django-rays/wiki/
Author: Russell Keith-Magee
Author-email: russell@keith-magee.com
License: UNKNOWN
Platform: UNKNOWN
Classifier: Development Status :: 1 - Planning
Classifier: Environment :: Web Environment
Classifier: Framework :: Django
Classifier: Intended Audience :: Developers
Classifier: License :: OSI Approved :: BSD License
Classifier: Operating System :: OS Independent
Classifier: Programming Language :: Python
Classifier: Topic :: Software Development :: Libraries :: Python Modules
Classifier: Topic :: Utilities
